wimsey/__init__.py
wimsey/_version.py
wimsey/config.py
wimsey/dataframe.py
wimsey/execution.py
wimsey/profiling.py
wimsey/py.typed
wimsey/tests.py
wimsey/types.py
wimsey-1.0.0.dist-info/METADATA
wimsey-1.0.0.dist-info/WHEEL
wimsey-1.0.0.dist-info/licenses/LICENSE
wimsey-1.0.0.dist-info/RECORD
