Metadata-Version: 2.4
Name: wimsey
Version: 1.0.0
Summary: A lightweight data contracts library
Author-email: Ben <benrutter@posteo.net>
License-File: LICENSE
Requires-Python: >=3.10
Requires-Dist: fsspec>=2024.10.0
Requires-Dist: narwhals>=1.10.0
